alpamyslinalg/__init__.py
alpamyslinalg/matrix.py
alpamyslinalg/threedmatrix.py
alpamyslinalg-0.1.4.dist-info/METADATA
alpamyslinalg-0.1.4.dist-info/WHEEL
alpamyslinalg-0.1.4.dist-info/top_level.txt
alpamyslinalg-0.1.4.dist-info/RECORD
