Metadata-Version: 2.4
Name: alpamyslinalg
Version: 0.1.4
Summary: Линейная алгебра: матрицы, СЛАУ и т.д.
Author: Алпамыс
Author-email: useralser90@gmail.com
Classifier: Programming Language :: Python :: 3
Classifier: License :: OSI Approved :: MIT License
Requires-Python: >=3.6
Dynamic: author
Dynamic: author-email
Dynamic: classifier
Dynamic: description
Dynamic: description-content-type
Dynamic: requires-python
Dynamic: summary
